[
  {
    "type": "constructor",
    "inputs": [
      {
        "name": "networkBaseTokenPriceInUsdProxyAggregator",
        "type": "address",
        "internalType": "address"
      },
      {
        "name": "marketReferenceCurrencyPriceInUsdProxyAggregator",
        "type": "address",
        "internalType": "address"
      }
    ],
    "stateMutability": "nonpayable"
  },
  {
    "type": "function",
    "name": "getGettersReportOne",
    "inputs": [],
    "outputs": [
      {
        "name": "",
        "type": "tuple",
        "internalType": "struct CreditifyV3GettersProcedureOne.GettersReportBatchOne",
        "components": [
          {
            "name": "walletBalanceProvider",
            "type": "address",
            "internalType": "address"
          },
          {
            "name": "uiIncentiveDataProvider",
            "type": "address",
            "internalType": "address"
          },
          {
            "name": "uiPoolDataProvider",
            "type": "address",
            "internalType": "address"
          }
        ]
      }
    ],
    "stateMutability": "view"
  }
]